stackit/serverupdate/__init__.py
stackit/serverupdate/api/__init__.py
stackit/serverupdate/api/default_api.py
stackit/serverupdate/api_client.py
stackit/serverupdate/api_response.py
stackit/serverupdate/configuration.py
stackit/serverupdate/exceptions.py
stackit/serverupdate/models/__init__.py
stackit/serverupdate/models/create_update_payload.py
stackit/serverupdate/models/create_update_schedule_payload.py
stackit/serverupdate/models/enable_service_resource_payload.py
stackit/serverupdate/models/error_response.py
stackit/serverupdate/models/get_update_policies_response.py
stackit/serverupdate/models/get_update_schedules_response.py
stackit/serverupdate/models/get_update_service_response.py
stackit/serverupdate/models/get_updates_list_response.py
stackit/serverupdate/models/update.py
stackit/serverupdate/models/update_policy.py
stackit/serverupdate/models/update_schedule.py
stackit/serverupdate/models/update_schedule_create_request.py
stackit/serverupdate/models/update_update_schedule_payload.py
stackit/serverupdate/py.typed
stackit/serverupdate/rest.py
stackit_serverupdate-1.1.0.dist-info/LICENSE.md
stackit_serverupdate-1.1.0.dist-info/METADATA
stackit_serverupdate-1.1.0.dist-info/NOTICE.txt
stackit_serverupdate-1.1.0.dist-info/WHEEL
stackit_serverupdate-1.1.0.dist-info/RECORD
